{
  "project_id": "universe",
  "releases": [
    {
      "version": "1.0.2",
      "tag": "universe.1.0.2",
      "url": "https://github.com/WCRP-CMIP/esgvoc_registry/releases/download/universe.1.0.2/universe-1.0.2.db",
      "checksum_sha256": "c832171c5b74df8acf5a56a4e61d02f78958b58e688a476766804f2b592261e4",
      "size_bytes": 12537856,
      "is_prerelease": false,
      "published_at": "2026-05-12T09:57:37Z",
      "universe_version": "1.0.2"
    },
    {
      "version": "v1.0.0",
      "tag": "universe.v1.0.0",
      "url": "https://github.com/WCRP-CMIP/esgvoc_registry/releases/download/universe.v1.0.0/universe-v1.0.0.db",
      "checksum_sha256": "ef3b8f64aab6f97d2132652c321a9e4ca5dc7f006a16790e5be3ea0c6bb6b59d",
      "size_bytes": 12525568,
      "is_prerelease": false,
      "published_at": "2026-04-22T07:29:45Z",
      "universe_version": "v1.0.0"
    },
    {
      "version": "dev-latest",
      "tag": "universe.dev-latest",
      "url": "https://github.com/WCRP-CMIP/esgvoc_registry/releases/download/universe.dev-latest/universe.db",
      "checksum_sha256": "165ecf69426522447ea9113c67a4271334f9b7ab02277f4f5d7e37cc4e9b0ce2",
      "size_bytes": 12537856,
      "is_prerelease": false,
      "published_at": "2026-04-21T16:11:57Z",
      "universe_version": "dev-latest"
    }
  ]
}
